AUTHORS
ChangeLog
LICENSE
README.md
requirements.txt
setup.cfg
setup.py
tox.ini
shoebox/__init__.py
shoebox/archive.py
shoebox/disk_storage.py
shoebox/handlers.py
shoebox/roll_checker.py
shoebox/roll_manager.py
shoebox.egg-info/PKG-INFO
shoebox.egg-info/SOURCES.txt
shoebox.egg-info/dependency_links.txt
shoebox.egg-info/not-zip-safe
shoebox.egg-info/pbr.json
shoebox.egg-info/requires.txt
shoebox.egg-info/top_level.txt
test/__init__.py
test/test_callbacks.py
test/test_disk_storage.py
test/test_roll_checker.py
test/test_roll_manager.py
test/integration/__init__.py
test/integration/test_json_tarball.py
test/integration/test_rolling.py
test/integration/templates/compute.instance.create.start_23.json
test/integration/templates/compute.instance.create.start_24.json
test/integration/templates/compute.instance.create.start_25.json
test/integration/templates/compute.instance.create.start_65.json
test/integration/templates/compute.instance.delete.start_7.json
test/integration/templates/compute.instance.delete.start_8.json
test/integration/templates/compute.instance.power_off.start_4.json
test/integration/templates/compute.instance.power_off.start_5.json
test/integration/templates/compute.instance.reboot.start_6.json
test/integration/templates/compute.instance.rebuild.start_14.json
test/integration/templates/compute.instance.rebuild.start_24.json
test/integration/templates/compute.instance.rescue.start_19.json
test/integration/templates/compute.instance.rescue.start_6.json
test/integration/templates/compute.instance.resize.confirm.start_12.json
test/integration/templates/compute.instance.resize.confirm.start_4.json
test/integration/templates/compute.instance.resize.prep.start_24.json
test/integration/templates/compute.instance.snapshot.start_7.json
test/integration/templates/compute.instance.snapshot.start_8.json
test/integration/templates/compute.instance.snapshot.start_9.json
test/integration/templates/compute.instance.unrescue.start_6.json
test/integration/templates/eod_exists.json