Metadata-Version: 1.1
Name: shoebox
Version: 0.6.dev51
Summary: data archiving library
Home-page: https://github.com/stackforge/stacktach-shoebox
Author: Dark Secret Software Inc.
Author-email: admin@darksecretsoftware.com
License: Apache-2
Keywords: json
Platform: UNKNOWN
Classifier: Development Status :: 3 - Alpha
Classifier: Environment :: Console
Classifier: Intended Audience :: Developers
Classifier: Intended Audience :: Information Technology
Classifier: License :: OSI Approved :: Apache Software License
Classifier: Operating System :: OS Independent
Classifier: Programming Language :: Python
Classifier: Topic :: Software Development :: Libraries :: Python Modules
